{
  "2026-02-06": [],
  "2026-02-13": [],
  "2026-02-20": [],
  "2026-02-27": [
    {
      "ticker": "CEG",
      "thesis": "Unit signs new 380 MW CyrusOne deal",
      "thesis_live": false,
      "exit_case": "Deal signed Feb 9 (already public)",
      "catalyst_resolved": true,
      "assessment": "CEG unit signed 380 MW CyrusOne PPA on Feb 9; reported this week",
      "exit_advice": "Exit; catalyst complete and priced in",
      "evidence_urls": [
        "https://www.insidermonkey.com/blog/constellation-energy-corporation-ceg-unit-signs-new-380-megawatt-deal-with-cyrusone-1703548/"
      ]
    }
  ],
  "2026-03-06": [],
  "2026-03-13": [
    {
      "ticker": "BWET",
      "thesis": "Hormuz risk lifts tanker day-rates",
      "thesis_live": true,
      "exit_case": "none",
      "catalyst_resolved": false,
      "assessment": "Catalyst remains live; BWET tracks ongoing Hormuz-driven tanker rate spike.",
      "exit_advice": "Exit once Hormuz risk visibly eases or day-rates roll over.",
      "evidence_urls": []
    }
  ],
  "2026-03-20": [
    {
      "ticker": "BWET",
      "thesis": "Hormuz risk lifts tanker day-rates",
      "thesis_live": true,
      "exit_case": "none",
      "catalyst_resolved": false,
      "assessment": "Catalyst remains live; no coverage this week.",
      "exit_advice": "Hold; no resolution evidence.",
      "evidence_urls": []
    }
  ],
  "2026-03-27": [
    {
      "ticker": "BWET",
      "thesis": "Hormuz risk lifts tanker day-rates",
      "thesis_live": true,
      "exit_case": "none",
      "catalyst_resolved": false,
      "assessment": "Catalyst ongoing per journal; BWET still tracks Hormuz-driven rates with zero new signals.",
      "exit_advice": "Hold; no resolution visible.",
      "evidence_urls": []
    }
  ],
  "2026-04-03": [
    {
      "ticker": "BWET",
      "thesis": "Hormuz risk lifts tanker day-rates",
      "thesis_live": true,
      "exit_case": "none",
      "catalyst_resolved": false,
      "assessment": "Journal shows catalyst ongoing with zero signals of decay or closure; BWET remains clean vehicle.",
      "exit_advice": "Hold; no resolution signal.",
      "evidence_urls": []
    }
  ],
  "2026-04-10": [
    {
      "ticker": "BWET",
      "thesis": "Hormuz risk lifts tanker day-rates",
      "thesis_live": true,
      "exit_case": "none",
      "catalyst_resolved": false,
      "assessment": "Catalyst unchanged; Hormuz tanker-rate support intact with no closure evidence.",
      "exit_advice": "Hold; no decay signals across journal.",
      "evidence_urls": []
    }
  ],
  "2026-04-17": [
    {
      "ticker": "BWET",
      "thesis": "Hormuz risk lifts tanker day-rates",
      "thesis_live": true,
      "exit_case": "none",
      "catalyst_resolved": false,
      "assessment": "Hormuz-driven rate support intact; BWET clean vehicle.",
      "exit_advice": "Hold; no resolution signals.",
      "evidence_urls": []
    }
  ],
  "2026-04-24": [
    {
      "ticker": "BWET",
      "thesis": "Hormuz risk lifts tanker day-rates",
      "thesis_live": true,
      "exit_case": "none",
      "catalyst_resolved": false,
      "assessment": "Hormuz tanker-rate support intact; BWET clean vehicle.",
      "exit_advice": "Hold; no resolution signal.",
      "evidence_urls": [
        "https://www.benzinga.com/markets/equities/26/04/51930047/nasdaq-snaps-13-session-win-streak-on-hormuz-tensions-investor-sentiment-improves-further-fear-index-in-greed-zone"
      ]
    }
  ],
  "2026-05-01": [
    {
      "ticker": "BWET",
      "thesis": "Hormuz risk lifts tanker day-rates",
      "thesis_live": true,
      "exit_case": "none",
      "catalyst_resolved": false,
      "assessment": "Hormuz rate support intact across full journal; BWET clean.",
      "exit_advice": "Hold; no resolution signals.",
      "evidence_urls": []
    }
  ],
  "2026-05-08": [
    {
      "ticker": "BWET",
      "thesis": "Hormuz risk lifts tanker day-rates",
      "thesis_live": true,
      "exit_case": "Potential Hormuz breakthrough reported, possibly resolving risk",
      "catalyst_resolved": false,
      "assessment": "Journal unchanged through May 1; this week's potential breakthrough is first signal of possible resolution but remains unconfirmed",
      "exit_advice": "Monitor for confirmed breakthrough; rates may normalize quickly",
      "evidence_urls": [
        "https://www.zerohedge.com/markets/crude-slips-amid-reports-potential-strait-hormuz-breakthrough-us-equity-futures-modestly"
      ]
    }
  ],
  "2026-05-15": [
    {
      "ticker": "BWET",
      "thesis": "Hormuz risk lifts tanker day-rates",
      "thesis_live": true,
      "exit_case": "none",
      "catalyst_resolved": false,
      "assessment": "Catalyst remains live per full journal with no resolution signals; 05-08 entry notes unconfirmed breakthrough only.",
      "exit_advice": "Exit only on confirmed closure of Hormuz risk or rate spike reversal.",
      "evidence_urls": []
    }
  ],
  "2026-05-22": [
    {
      "ticker": "BWET",
      "thesis": "Hormuz risk lifts tanker day-rates",
      "thesis_live": true,
      "exit_case": "none",
      "catalyst_resolved": false,
      "assessment": "Rates remain elevated on ongoing Hormuz tensions per this week's note and entire journal; catalyst pending.",
      "exit_advice": "Hold; no closure evidence.",
      "evidence_urls": []
    }
  ],
  "2026-05-29": [
    {
      "ticker": "BWET",
      "thesis": "Hormuz risk lifts tanker day-rates",
      "thesis_live": true,
      "exit_case": "none",
      "catalyst_resolved": false,
      "assessment": "Hormuz risk and elevated tanker rates remain intact; 05-08 unconfirmed breakthrough did not close catalyst.",
      "exit_advice": "Hold; no resolution signals across journal.",
      "evidence_urls": []
    },
    {
      "ticker": "CLOV",
      "thesis": "Wins lawsuit on Star Ratings",
      "thesis_live": false,
      "exit_case": "Lawsuit won and announced this week",
      "catalyst_resolved": true,
      "assessment": "Catalyst occurred on 2026-05-29 per news; no pending element remains",
      "exit_advice": "Exit immediately; catalyst fully resolved",
      "evidence_urls": [
        "https://www.insidermonkey.com/blog/clover-health-clov-wins-lawsuit-on-star-ratings-soars-to-record-high-1770686/"
      ]
    }
  ],
  "2026-06-05": [
    {
      "ticker": "BWET",
      "thesis": "Hormuz risk lifts tanker day-rates",
      "thesis_live": true,
      "exit_case": "none",
      "catalyst_resolved": false,
      "assessment": "Hormuz risk and elevated tanker rates unchanged per full journal; 05-08 unconfirmed note did not close catalyst.",
      "exit_advice": "Hold; no resolution signals.",
      "evidence_urls": []
    },
    {
      "ticker": "QBTS",
      "thesis": "US gov $2B quantum funding push",
      "thesis_live": false,
      "exit_case": "Funding push publicly announced 6/3 and allocated",
      "catalyst_resolved": true,
      "assessment": "Catalyst occurred at announcement; no pending discrete event remains",
      "exit_advice": "Exit immediately; catalyst is public and priced-in",
      "evidence_urls": [
        "https://www.fool.com/investing/2026/06/02/the-us-government-just-plowed-2-billion-into-9/",
        "https://www.foreignpolicyjournal.com/2026/06/02/u-s-department-of-commerces-2b-quantum-push-places-d-wave-nyse-qbts-and-honeywell-nasdaq-hon-quantinuum-in-focus/"
      ]
    }
  ],
  "2026-06-12": [
    {
      "ticker": "BWET",
      "thesis": "Hormuz risk lifts tanker day-rates",
      "thesis_live": true,
      "exit_case": "none",
      "catalyst_resolved": false,
      "assessment": "Full journal through 06-05 shows catalyst unresolved; 05-08 unconfirmed note did not close it and later entries confirm persistence. No fresh coverage this week.",
      "exit_advice": "Hold; no exit trigger met.",
      "evidence_urls": []
    }
  ],
  "2026-06-19": [
    {
      "ticker": "BWET",
      "thesis": "Hormuz risk lifts tanker day-rates",
      "thesis_live": true,
      "exit_case": "none",
      "catalyst_resolved": false,
      "assessment": "Hormuz-driven rate support fully intact; 05-08 note never closed catalyst.",
      "exit_advice": "Hold; no resolution signals across journal.",
      "evidence_urls": []
    }
  ],
  "2026-06-26": [
    {
      "ticker": "BWET",
      "thesis": "Hormuz risk lifts tanker day-rates",
      "thesis_live": true,
      "exit_case": "none",
      "catalyst_resolved": false,
      "assessment": "Hormuz risk intact, rates elevated.",
      "exit_advice": "Hold; no resolution signal.",
      "evidence_urls": [
        "https://www.actionforex.com/contributors/fundamental-analysis/645245-iran-strikes-ship-near-hormuz-reaction-muted/"
      ]
    }
  ],
  "2026-07-03": [
    {
      "ticker": "BWET",
      "thesis": "Hormuz risk lifts tanker day-rates",
      "thesis_live": true,
      "exit_case": "none",
      "catalyst_resolved": false,
      "assessment": "Hormuz risk and tanker-rate support fully intact across every entry; 05-08 note never closed catalyst and later weeks confirm persistence.",
      "exit_advice": "Hold; no resolution in full journal.",
      "evidence_urls": []
    }
  ]
}